rusty_chrono-0.1.4.dist-info/METADATA
rusty_chrono-0.1.4.dist-info/WHEEL
rusty_chrono-0.1.4.dist-info/license_files/LICENSE
rusty_chrono/__init__.py
rusty_chrono/rusty_chrono.cpython-311-aarch64-linux-gnu.so
rusty_chrono-0.1.4.dist-info/RECORD
